{
  "schemaVersion": 1,
  "category": "supabase",
  "updatedAt": "2025-08-31",
  "subcategories": [
    {
      "slug": "general",
      "name": "通用服务",
      "items": [
        {
          "title": "资源导航",
          "url": "../index.html",
          "isFree": false,
          "isOpenSource": false,
          "id": "资源导航",
          "updatedAt": "2025-08-31",
          "region": "global"
        },
        {
          "title": "首页",
          "url": "../index.html",
          "isFree": false,
          "isOpenSource": false,
          "id": "首页",
          "updatedAt": "2025-08-31",
          "region": "global"
        },
        {
          "title": "访问官网",
          "url": "https://supabase.com/",
          "isFree": true,
          "isOpenSource": false,
          "id": "访问官网",
          "updatedAt": "2025-08-31",
          "region": "global"
        },
        {
          "title": "资源分类",
          "url": "#",
          "isFree": false,
          "isOpenSource": false,
          "id": "资源分类",
          "updatedAt": "2025-08-31",
          "region": "global"
        },
        {
          "title": "Backend服务",
          "url": "#",
          "isFree": false,
          "isOpenSource": false,
          "id": "backend服务",
          "updatedAt": "2025-08-31",
          "region": "global"
        },
        {
          "title": "关于 Supabase",
          "url": "https://supabase.com/",
          "description": "Supabase 是一个开源的 Firebase 替代品，提供完整的后端解决方案，包括 PostgreSQL 数据库、身份验证、存储、边缘函数等功能。其免费计划为开发者提供了一个低门槛体验企业级后端服务的机会，非常适合个人项目、MVP开发和学习使用。",
          "tags": [
            "开源",
            "PostgreSQL",
            "后端即服务",
            "实时数据库"
          ],
          "isFree": true,
          "isOpenSource": true,
          "id": "关于-supabase",
          "updatedAt": "2025-08-31",
          "region": "global"
        },
        {
          "title": "数据库存储",
          "url": "https://supabase.com/",
          "isFree": false,
          "isOpenSource": false,
          "id": "数据库存储",
          "updatedAt": "2025-08-31",
          "region": "global"
        },
        {
          "title": "文件存储",
          "url": "https://supabase.com/",
          "isFree": false,
          "isOpenSource": false,
          "id": "文件存储",
          "updatedAt": "2025-08-31",
          "region": "global"
        },
        {
          "title": "带宽限制",
          "url": "https://supabase.com/",
          "isFree": false,
          "isOpenSource": false,
          "id": "带宽限制",
          "updatedAt": "2025-08-31",
          "region": "global"
        },
        {
          "title": "活跃用户",
          "url": "https://supabase.com/",
          "isFree": false,
          "isOpenSource": false,
          "id": "活跃用户",
          "updatedAt": "2025-08-31",
          "region": "global"
        },
        {
          "title": "边缘函数",
          "url": "https://supabase.com/",
          "isFree": false,
          "isOpenSource": false,
          "id": "边缘函数",
          "updatedAt": "2025-08-31",
          "region": "global"
        },
        {
          "title": "项目数量",
          "url": "https://supabase.com/",
          "isFree": false,
          "isOpenSource": false,
          "id": "项目数量",
          "updatedAt": "2025-08-31",
          "region": "global"
        },
        {
          "title": "项目数量限制",
          "url": "https://supabase.com/",
          "description": "每个组织最多只能创建 2 个免费项目，超出需要升级到付费计划或创建新组织。",
          "isFree": true,
          "isOpenSource": false,
          "id": "项目数量限制",
          "updatedAt": "2025-08-31",
          "region": "global"
        },
        {
          "title": "项目自动暂停",
          "url": "https://supabase.com/",
          "description": "如果项目连续 7 天未使用，系统将自动暂停该项目，需要手动重新激活。",
          "isFree": false,
          "isOpenSource": false,
          "id": "项目自动暂停",
          "updatedAt": "2025-08-31",
          "region": "global"
        },
        {
          "title": "功能限制",
          "url": "https://supabase.com/",
          "description": "免费计划不支持自定义域名、自动备份、日志保留超过 1 天等高级功能。",
          "isFree": true,
          "isOpenSource": false,
          "id": "功能限制",
          "updatedAt": "2025-08-31",
          "region": "global"
        },
        {
          "title": "边缘函数限制",
          "url": "https://supabase.com/",
          "description": "每个项目最多 100 个边缘函数，最大内存 256MB，最大执行时间 150 秒。",
          "isFree": false,
          "isOpenSource": false,
          "id": "边缘函数限制",
          "updatedAt": "2025-08-31",
          "region": "global"
        },
        {
          "title": "邮件发送限制",
          "url": "https://supabase.com/",
          "description": "每月最多发送 1,000 封邮件，超出需使用自定义 SMTP 服务（如 SendGrid 或 Mailgun）。",
          "isFree": false,
          "isOpenSource": false,
          "id": "邮件发送限制",
          "updatedAt": "2025-08-31",
          "region": "global"
        },
        {
          "title": "https://supabase.com/",
          "url": "https://supabase.com/",
          "isFree": false,
          "isOpenSource": false,
          "id": "https:--supabasecom-",
          "updatedAt": "2025-08-31",
          "region": "global"
        },
        {
          "title": "保持项目活跃",
          "url": "https://supabase.com/",
          "description": "定期访问项目或设置自动化任务，避免 7 天未使用导致项目被自动暂停。可利用 GitHub Actions 设置每周访问检查。",
          "isFree": false,
          "isOpenSource": false,
          "id": "保持项目活跃",
          "updatedAt": "2025-08-31",
          "region": "global"
        },
        {
          "title": "合理规划资源",
          "url": "https://supabase.com/",
          "description": "在免费计划限制内进行开发，优化数据库查询，压缩存储文件，避免超出配额导致服务中断。",
          "isFree": true,
          "isOpenSource": false,
          "id": "合理规划资源",
          "updatedAt": "2025-08-31",
          "region": "global"
        },
        {
          "title": "使用自定义 SMTP 服务",
          "url": "https://supabase.com/",
          "description": "当需要发送大量邮件时，配置外部 SMTP 服务（如 SendGrid 免费计划）绕过每月 1,000 封的限制。",
          "isFree": true,
          "isOpenSource": false,
          "id": "使用自定义-smtp-服务",
          "updatedAt": "2025-08-31",
          "region": "global"
        },
        {
          "title": "监控使用情况",
          "url": "https://supabase.com/",
          "description": "通过 Dashboard 定期查看资源使用情况，设置使用阈值提醒，及时调整资源消耗较大的功能。",
          "isFree": false,
          "isOpenSource": false,
          "id": "监控使用情况",
          "updatedAt": "2025-08-31",
          "region": "global"
        },
        {
          "title": "利用社区支持",
          "url": "https://supabase.com/",
          "description": "在 GitHub Discussions 或 Discord 社区寻求帮助，这是免费计划获取技术支持的主要渠道。",
          "isFree": true,
          "isOpenSource": false,
          "id": "利用社区支持",
          "updatedAt": "2025-08-31",
          "region": "global"
        },
        {
          "title": "多环境策略",
          "url": "https://supabase.com/",
          "description": "利用 2 个免费项目配额，分别创建开发和生产环境，避免开发测试影响生产数据。",
          "isFree": true,
          "isOpenSource": false,
          "id": "多环境策略",
          "updatedAt": "2025-08-31",
          "region": "global"
        },
        {
          "title": "资源导航",
          "url": "https://github.com/guomengtao/rinuo.com",
          "isFree": false,
          "isOpenSource": false,
          "id": "资源导航",
          "updatedAt": "2025-08-31",
          "region": "global"
        }
      ]
    }
  ]
}